{"name": "", "room": "Cafe", "id": "091b9085c836e19e", "tables": [{"x": 200, "y": 400, "bordType": "langbord", "rotation": 30, "descriptor": "A"}, {"x": 300, "y": 400, "bordType": "langbord", "rotation": 30, "descriptor": "B"}, {"x": 400, "y": 400, "bordType": "langbord", "rotation": 30, "descriptor": "C"}, {"x": 500, "y": 400, "bordType": "langbord", "rotation": 30, "descriptor": "D"}], "date": {"exact": 1595240758109, "display": "12:25 20.7.2020"}, "statistics": {"bord": {"langbord": 4, "rundbord": 0}, "gjester": {"antall": 32}}}